{"basics":{"name":"Shamanthak Hegde","label":"Master's in Computer Science Student","image":"","email":"shegde23@asu.edu","phone":"+1 (602)-637-8364","url":"https://shamanthak-hegde.github.io","summary":"A German-born theoretical physicist, widely ranked among the greatest and most influential scientists of all time","location":{"address":"711 Broadway Rd","postalCode":"AZ 85282","city":"Tempe","countryCode":"US","region":"Arizona"},"profiles":[{"network":"Twitter","username":"AlbertEinstein","url":"https://twitter.com/AlbertEinstein"}]},"work":[{"name":"Bosch Global Software Technologies","position":"Software Engineering Intern","url":"https://www.bosch-softwaretechnologies.com/en/","startDate":"2023-02","endDate":"2023-05","summary":"","highlights":["Worked on a product DeviceBridge that collects data from shop floor devices and deliver it to upstream servers.","Developed a Python scripting feature for users to write business logics on the data in Python, with C# and .NET.","Explored ways for faster data acquisition."]}],"volunteer":[],"education":[{"institution":"Arizona State University, Tempe, USA","url":"https://www.asu.edu/","area":"Computer Science","studyType":"Master of Science","startDate":"2023-08","endDate":"Present","score":"","courses":["Topics in NLP","Perceptual Reasoning and Symbol Grounding","Software Design"]},{"institution":"KLE Technological University, Hubballi, India","url":"https://www.kletech.ac.in/hubballi/","area":"Computer Science","studyType":"Bachelor of Engineering","startDate":"2019","endDate":"2023","score":"8.18/10","courses":[]}],"awards":[{"title":"Nobel Prize in Physics","date":"1921-11-01","awarder":"Royal Swedish Academy of Sciences","summary":"The Nobel Prizes are five separate prizes that, according to Alfred Nobel's will of 1895, are awarded to 'those who, during the preceding year, have conferred the greatest benefit to humankind.'"}],"certificates":[],"publications":[],"skills":[],"languages":[{"language":"Kannada","fluency":"Native Speaker"},{"language":"English","fluency":"Fluent"},{"language":"Hindi","fluency":"Fluent"}],"interests":[],"references":[],"projects":[]}